asyncio_https_proxy/__init__.py
asyncio_https_proxy/chunked_encoding.py
asyncio_https_proxy/http_header.py
asyncio_https_proxy/http_request.py
asyncio_https_proxy/http_response.py
asyncio_https_proxy/https_forward_proxy_handler.py
asyncio_https_proxy/https_proxy_handler.py
asyncio_https_proxy/server.py
asyncio_https_proxy/tls_store.py
asyncio_https_proxy-0.1.1.dist-info/licenses/LICENSE
asyncio_https_proxy-0.1.1.dist-info/METADATA
asyncio_https_proxy-0.1.1.dist-info/WHEEL
asyncio_https_proxy-0.1.1.dist-info/top_level.txt
asyncio_https_proxy-0.1.1.dist-info/RECORD
