Metadata-Version: 2.4
Name: asyncio-https-proxy
Version: 0.1.1
Summary: Embeddable asyncio HTTPS forward proxy with request/response interception for Python applications
Requires-Python: >=3.13
License-File: LICENSE
Requires-Dist: cryptography>=45.0.7
Dynamic: license-file
